wayforpay/__init__.py
wayforpay/invoice.py
wayforpay/payments.py
wayforpay/utils.py
wayforpay/wayforpay.py
wayforpay_python-1.0.1.dist-info/LICENSE
wayforpay_python-1.0.1.dist-info/METADATA
wayforpay_python-1.0.1.dist-info/WHEEL
wayforpay_python-1.0.1.dist-info/top_level.txt
wayforpay_python-1.0.1.dist-info/RECORD
