Metadata-Version: 2.1
Name: wayforpay-python
Version: 1.0.1
Summary: SDK for WayForPay API
Home-page: https://github.com/RympeR/wayforpay_python
Author: RympeR
Author-email: georg.rashkov@gmail.com
License: MIT
Platform: UNKNOWN
Classifier: License :: OSI Approved :: MIT License
Classifier: Programming Language :: Python :: 3
Classifier: Programming Language :: Python :: 3.7
